odoo/addons/eater_member_card/README.rst
odoo/addons/eater_member_card/__init__.py
odoo/addons/eater_member_card/__manifest__.py
odoo/addons/eater_member_card/i18n/eater_member_card.pot
odoo/addons/eater_member_card/i18n/fr.po
odoo/addons/eater_member_card/migrations/12.0.1.1.0/post-migration.py
odoo/addons/eater_member_card/models/__init__.py
odoo/addons/eater_member_card/models/partner.py
odoo/addons/eater_member_card/readme/CONTRIBUTORS.rst
odoo/addons/eater_member_card/readme/DESCRIPTION.rst
odoo/addons/eater_member_card/readme/newsfragments/477.bugfix.rst
odoo/addons/eater_member_card/report/member_card_template.xml
odoo/addons/eater_member_card/static/description/index.html
odoo/addons/eater_member_card/views/partner.xml
odoo12_addon_eater_member_card-12.0.1.1.0.dist-info/METADATA
odoo12_addon_eater_member_card-12.0.1.1.0.dist-info/WHEEL
odoo12_addon_eater_member_card-12.0.1.1.0.dist-info/top_level.txt
odoo12_addon_eater_member_card-12.0.1.1.0.dist-info/RECORD
